odoo/addons/fieldservice_agreement_helpdesk_mgmt/README.rst
odoo/addons/fieldservice_agreement_helpdesk_mgmt/__init__.py
odoo/addons/fieldservice_agreement_helpdesk_mgmt/__manifest__.py
odoo/addons/fieldservice_agreement_helpdesk_mgmt/i18n/fieldservice_agreement_helpdesk_mgmt.pot
odoo/addons/fieldservice_agreement_helpdesk_mgmt/i18n/it.po
odoo/addons/fieldservice_agreement_helpdesk_mgmt/i18n/pt.po
odoo/addons/fieldservice_agreement_helpdesk_mgmt/i18n/pt_BR.po
odoo/addons/fieldservice_agreement_helpdesk_mgmt/i18n/pt_PT.po
odoo/addons/fieldservice_agreement_helpdesk_mgmt/models/__init__.py
odoo/addons/fieldservice_agreement_helpdesk_mgmt/models/helpdesk_ticket.py
odoo/addons/fieldservice_agreement_helpdesk_mgmt/readme/CONTRIBUTORS.rst
odoo/addons/fieldservice_agreement_helpdesk_mgmt/readme/CREDITS.rst
odoo/addons/fieldservice_agreement_helpdesk_mgmt/readme/DESCRIPTION.rst
odoo/addons/fieldservice_agreement_helpdesk_mgmt/readme/USAGE.rst
odoo/addons/fieldservice_agreement_helpdesk_mgmt/static/description/banner.png
odoo/addons/fieldservice_agreement_helpdesk_mgmt/static/description/icon.png
odoo/addons/fieldservice_agreement_helpdesk_mgmt/static/description/index.html
odoo/addons/fieldservice_agreement_helpdesk_mgmt/tests/__init__.py
odoo/addons/fieldservice_agreement_helpdesk_mgmt/tests/test_fieldservice_agreement_helpdesk_mgmt.py
odoo/addons/fieldservice_agreement_helpdesk_mgmt/views/helpdesk_ticket.xml
odoo12_addon_fieldservice_agreement_helpdesk_mgmt-12.0.1.0.0.99.dev13.dist-info/METADATA
odoo12_addon_fieldservice_agreement_helpdesk_mgmt-12.0.1.0.0.99.dev13.dist-info/WHEEL
odoo12_addon_fieldservice_agreement_helpdesk_mgmt-12.0.1.0.0.99.dev13.dist-info/top_level.txt
odoo12_addon_fieldservice_agreement_helpdesk_mgmt-12.0.1.0.0.99.dev13.dist-info/RECORD
